modelsensor/__init__.py
modelsensor/cli.py
modelsensor/core.py
modelsensor/formatters.py
modelsensor-1.1.1.dist-info/licenses/LICENSE
modelsensor-1.1.1.dist-info/METADATA
modelsensor-1.1.1.dist-info/WHEEL
modelsensor-1.1.1.dist-info/entry_points.txt
modelsensor-1.1.1.dist-info/top_level.txt
modelsensor-1.1.1.dist-info/RECORD
