Metadata-Version: 2.4
Name: modelsensor
Version: 1.1.1
Summary: Let LLM sense the world - System information detection for AI models
Author-email: Frederick <wedonotuse@outlook.com>
License: MIT License
Project-URL: Homepage, https://github.com/EasyCam/modelsensor
Project-URL: Repository, https://github.com/EasyCam/modelsensor
Project-URL: Issues, https://github.com/EasyCam/modelsensor/issues
Project-URL: Documentation, https://github.com/EasyCam/modelsensor#readme
Keywords: system,monitoring,AI,LLM,ollama,system-information,sensors
Classifier: Development Status :: 4 - Beta
Classifier: Intended Audience :: Developers
Classifier: Topic :: System :: Monitoring
Classifier: Topic :: System :: Systems Administration
Classifier: License :: OSI Approved :: MIT License
Classifier: Programming Language :: Python :: 3
Classifier: Programming Language :: Python :: 3.7
Classifier: Programming Language :: Python :: 3.8
Classifier: Programming Language :: Python :: 3.9
Classifier: Programming Language :: Python :: 3.10
Classifier: Programming Language :: Python :: 3.11
Classifier: Programming Language :: Python :: 3.12
Classifier: Operating System :: OS Independent
Requires-Python: >=3.7
License-File: LICENSE
Requires-Dist: psutil>=5.8.0
Requires-Dist: requests>=2.25.0
Provides-Extra: dev
Requires-Dist: pytest>=6.0; extra == "dev"
Requires-Dist: pytest-cov; extra == "dev"
Requires-Dist: black; extra == "dev"
Requires-Dist: flake8; extra == "dev"
Requires-Dist: build; extra == "dev"
Requires-Dist: twine; extra == "dev"
Dynamic: license-file
